src/one_bit/nand_gate.sv
`timescale 1ns / 1ps

module NAND_Gate_logic(
  input logic a_in,
  input logic b_in,
  output logic a_out
);

  always_comb begin
    a_out = ~(a_in & b_in);
  end

endmodule


module NAND_Gate_bit(
  input bit a_in,
  input bit b_in,
  output bit a_out
);

  always_comb begin
    a_out = ~(a_in & b_in);
  end

endmodule

src/memory/sr_latch.sv
`timescale 1ns / 1ps

module SR_Latch(
    input logic s_in,
    input logic r_in,
    output logic a_out
);
    logic r_out;
    logic s_out;
    NAND_Gate_logic s(
        .a_in(s_in),
        .b_in(r_out),
        .a_out(s_out)
    );

    NAND_Gate_logic r(
        .a_in(r_in),
        .b_in(s_out),
        .a_out(r_out)
    );

    assign a_out = s_out;

endmodule

src/elements/mux_1op.sv
`timescale 1ns / 1ps

import constants::*;

module MUX_1_Op_Multi_logic(
    input logic[ARCHITECTURE_WIDTH - 1: 0]  a_in,
    input logic[ARCHITECTURE_WIDTH - 1: 0]  b_in,
    input logic                             op_in,
    output logic[ARCHITECTURE_WIDTH - 1: 0] a_out
);

    always_comb begin
        unique case (op_in)
            1'b0: a_out = a_in;
            1'b1: a_out = b_in;
            default: a_out = '0;
        endcase
    end

endmodule

module MUX_1_Op_Multi_single(
    input logic  a_in,
    input logic  b_in,
    input logic op_in,
    output logic a_out
);

    always_comb begin
        unique case (op_in)
            1'b0: a_out = a_in;
            1'b1: a_out = b_in;
            default: a_out = '0;
        endcase
    end

endmodule

src/one_bit/not_gate.sv
`timescale 1ns / 1ps

module NOT_Gate_logic(
  input logic a_in,
  output logic a_out
);

  always_comb begin
    a_out = ~a_in;
  end

endmodule


module NOT_Gate_bit(
  input bit a_in,
  output bit a_out
);

  always_comb begin
    a_out = ~a_in;
  end

endmodule

src/memory/d_latch.sv
`timescale 1ns / 1ps

module D_Latch(
    input logic     a_in, //data signal
    input logic     e_in, //clock signal
    input logic     rst_in, //reset signal
    output logic    a_out   //out signal
);
    //Data handle path controlled by clock
    logic b_in_out;
    NOT_Gate_logic a_inv(
        .a_in(a_in),
        .a_out(b_in_out)
    );

    logic a_out_enabled;
    logic b_out_enabled;
    NAND_Gate_logic a_enabled(
        .a_in(a_in),
        .b_in(e_in),
        .a_out(a_out_enabled)
    );

    NAND_Gate_logic b_enabled(
        .a_in(b_in_out),
        .b_in(e_in),
        .a_out(b_out_enabled)
    );

    //combine 2 paths
    logic a_out_rst;
    logic b_out_rst;
    // MUX_1_Op_Multi_single in_1(
    //     .a_in(a_out_enabled),
    //     .b_in(1'b0),
    //     .op_in(rst_in),
    //     .a_out(a_out_rst)
    // );
    // MUX_1_Op_Multi_single in_2(
    //     .a_in(b_out_enabled),
    //     .b_in(1'b1),
    //     .op_in(rst_in),
    //     .a_out(b_out_rst)
    // );

    MUX_1_Op_Multi_single in_1(
        .a_in(a_out_enabled),
        .b_in(1'b1),
        .op_in(rst_in),
        .a_out(a_out_rst)
    );

    MUX_1_Op_Multi_single in_2(
        .a_in(b_out_enabled),
        .b_in(1'b0),
        .op_in(rst_in),
        .a_out(b_out_rst)
    );
   
    SR_Latch sr(
        .s_in(a_out_rst),
        .r_in(b_out_rst),
        .a_out(a_out)
    );

endmodule

src/memory/d_flip_flop.sv
`timescale 1ns / 1ps

module D_Flip_flop(
    input  logic clk,
    input  logic rst_in,
    input  logic load_in,
    input  logic d_in,
    output logic q_out
);
    logic clk_inv;
    NOT_Gate_logic not_clk(
        .a_in (clk),
        .a_out(clk_inv)
    );

    logic d_selected;
    MUX_1_Op_Multi_single d_mux(
        .a_in (q_out),
        .b_in (d_in),      
        .op_in(load_in),
        .a_out(d_selected)
    );

    logic master_latch_out;
    D_Latch master_latch (
        .a_in  (d_selected),
        .e_in  (clk_inv),
        .rst_in(rst_in),
        .a_out (master_latch_out)
    );

    logic slave_latch_out;
    D_Latch slave_latch(
        .a_in  (master_latch_out),
        .e_in  (clk),
        .rst_in(rst_in),
        .a_out (slave_latch_out)
    );

    assign q_out = slave_latch_out;

endmodule

tb/d_flip_flop_tb.sv
`timescale 1ns / 1ps

module d_flip_flop_tb;
    logic clk;
    logic rst_in;
    logic load_in;
    logic d_in;
    logic q_out;

    D_Flip_flop dut (
        .clk(clk), .rst_in(rst_in), .load_in(load_in),
        .d_in(d_in), .q_out(q_out)
    );

    always #5 clk = ~clk;

    task automatic check(input logic expected, input string name);
        if (q_out !== expected)
            $fatal(1, "%s: expected %b, got %b", name, expected, q_out);
        $display("PASS: %s", name);
    endtask

    initial begin
        $dumpfile("d_flip_flop_tb.vcd");
        $dumpvars(0, d_flip_flop_tb);
        clk = 1'b0;
        rst_in = 1'b1;
        load_in = 1'b0;
        d_in = 1'b0;
        #1;
        check(1'b0, "reset clears output");

        rst_in = 1'b0;
        load_in = 1'b1;
        d_in = 1'b1;
        @(posedge clk);
        #1;
        check(1'b1, "loads one on rising edge");

        d_in = 1'b0;
        #2;
        check(1'b1, "ignores data between edges");
        @(posedge clk);
        #1;
        check(1'b0, "loads zero on rising edge");

        load_in = 1'b0;
        d_in = 1'b1;
        @(posedge clk);
        #1;
        check(1'b0, "holds value when load is disabled");
        $display("D_Flip_flop test completed successfully");
        $finish;
    end
endmodule

d_flip_flop_tb.vcd
$version Generated by VerilatedVcd $end
$timescale 1ps $end
 $scope module TOP $end
  $scope module d_flip_flop_tb $end
   $var wire 1 - clk $end
   $var wire 1 . rst_in $end
   $var wire 1 / load_in $end
   $var wire 1 0 d_in $end
   $var wire 1 ' q_out $end
   $scope module dut $end
    $var wire 1 - clk $end
    $var wire 1 . rst_in $end
    $var wire 1 / load_in $end
    $var wire 1 0 d_in $end
    $var wire 1 ' q_out $end
    $var wire 1 1 clk_inv $end
    $var wire 1 # d_selected $end
    $var wire 1 ( master_latch_out $end
    $var wire 1 ' slave_latch_out $end
    $scope module d_mux $end
     $var wire 1 ' a_in $end
     $var wire 1 0 b_in $end
     $var wire 1 / op_in $end
     $var wire 1 # a_out $end
    $upscope $end
    $scope module master_latch $end
     $var wire 1 # a_in $end
     $var wire 1 1 e_in $end
     $var wire 1 . rst_in $end
     $var wire 1 ( a_out $end
     $var wire 1 $ b_in_out $end
     $var wire 1 2 a_out_enabled $end
     $var wire 1 3 b_out_enabled $end
     $var wire 1 % a_out_rst $end
     $var wire 1 & b_out_rst $end
     $scope module a_enabled $end
      $var wire 1 # a_in $end
      $var wire 1 1 b_in $end
      $var wire 1 2 a_out $end
     $upscope $end
     $scope module a_inv $end
      $var wire 1 # a_in $end
      $var wire 1 $ a_out $end
     $upscope $end
     $scope module b_enabled $end
      $var wire 1 $ a_in $end
      $var wire 1 1 b_in $end
      $var wire 1 3 a_out $end
     $upscope $end
     $scope module in_1 $end
      $var wire 1 2 a_in $end
      $var wire 1 7 b_in $end
      $var wire 1 . op_in $end
      $var wire 1 % a_out $end
     $upscope $end
     $scope module in_2 $end
      $var wire 1 3 a_in $end
      $var wire 1 8 b_in $end
      $var wire 1 . op_in $end
      $var wire 1 & a_out $end
     $upscope $end
     $scope module sr $end
      $var wire 1 % s_in $end
      $var wire 1 & r_in $end
      $var wire 1 ( a_out $end
      $var wire 1 4 r_out $end
      $var wire 1 ( s_out $end
      $scope module r $end
       $var wire 1 & a_in $end
       $var wire 1 ( b_in $end
       $var wire 1 4 a_out $end
      $upscope $end
      $scope module s $end
       $var wire 1 % a_in $end
       $var wire 1 4 b_in $end
       $var wire 1 ( a_out $end
      $upscope $end
     $upscope $end
    $upscope $end
    $scope module not_clk $end
     $var wire 1 - a_in $end
     $var wire 1 1 a_out $end
    $upscope $end
    $scope module slave_latch $end
     $var wire 1 ( a_in $end
     $var wire 1 - e_in $end
     $var wire 1 . rst_in $end
     $var wire 1 ' a_out $end
     $var wire 1 ) b_in_out $end
     $var wire 1 5 a_out_enabled $end
     $var wire 1 6 b_out_enabled $end
     $var wire 1 * a_out_rst $end
     $var wire 1 + b_out_rst $end
     $scope module a_enabled $end
      $var wire 1 ( a_in $end
      $var wire 1 - b_in $end
      $var wire 1 5 a_out $end
     $upscope $end
     $scope module a_inv $end
      $var wire 1 ( a_in $end
      $var wire 1 ) a_out $end
     $upscope $end
     $scope module b_enabled $end
      $var wire 1 ) a_in $end
      $var wire 1 - b_in $end
      $var wire 1 6 a_out $end
     $upscope $end
     $scope module in_1 $end
      $var wire 1 5 a_in $end
      $var wire 1 7 b_in $end
      $var wire 1 . op_in $end
      $var wire 1 * a_out $end
     $upscope $end
     $scope module in_2 $end
      $var wire 1 6 a_in $end
      $var wire 1 8 b_in $end
      $var wire 1 . op_in $end
      $var wire 1 + a_out $end
     $upscope $end
     $scope module sr $end
      $var wire 1 * s_in $end
      $var wire 1 + r_in $end
      $var wire 1 ' a_out $end
      $var wire 1 , r_out $end
      $var wire 1 ' s_out $end
      $scope module r $end
       $var wire 1 + a_in $end
       $var wire 1 ' b_in $end
       $var wire 1 , a_out $end
      $upscope $end
      $scope module s $end
       $var wire 1 * a_in $end
       $var wire 1 , b_in $end
       $var wire 1 ' a_out $end
      $upscope $end
     $upscope $end
    $upscope $end
   $upscope $end
  $upscope $end
 $upscope $end
$enddefinitions $end


#0
0#
1$
1%
0&
0'
0(
1)
1*
0+
1,
0-
1.
0/
00
11
12
03
14
15
16
17
08
#1000
1#
0$
0%
1&
1(
0)
1+
0.
1/
10
02
13
04
#5000
1%
1'
0*
0,
1-
01
12
05
#6000
0#
1$
00
#8000
#10000
0&
0(
1)
1*
0-
11
03
14
15
#15000
1&
0'
0+
1,
1-
01
13
06
#16000
0/
10
#20000
0&
1+
0-
11
03
16
#25000
1&
0+
1-
01
13
06
